flask_applicationinsights.py
Flask_ApplicationInsights-0.2.4.dist-info/METADATA
Flask_ApplicationInsights-0.2.4.dist-info/RECORD
Flask_ApplicationInsights-0.2.4.dist-info/WHEEL
Flask_ApplicationInsights-0.2.4.dist-info/top_level.txt
