Metadata-Version: 2.1
Name: Flask-ApplicationInsights
Version: 0.2.4
Summary: Microsoft Azure Application Insights integration for Flask.
Home-page: https://github.com/gghez/flask_applicationinsights
Author: Gregory Ghez
Author-email: gregory.ghez@gmail.com
License: MIT
Platform: any
Classifier: Environment :: Web Environment
Classifier: Intended Audience :: Developers
Classifier: License :: OSI Approved :: MIT License
Classifier: Operating System :: OS Independent
Classifier: Programming Language :: Python :: 3
Classifier: Topic :: Internet :: WWW/HTTP :: Dynamic Content
Classifier: Topic :: Software Development :: Libraries :: Python Modules
Requires-Dist: Flask (>=1.0.2)
Requires-Dist: applicationinsights (==0.11.6)
